lerobot_surgery/__init__.py
lerobot_surgery/__version__.py
lerobot_surgery/cli.py
lerobot_surgery/v3/__init__.py
lerobot_surgery/v3/merge.py
lerobot_surgery/v3/remove.py
lerobot_surgery-0.1.0.dist-info/licenses/LICENSE
lerobot_surgery-0.1.0.dist-info/METADATA
lerobot_surgery-0.1.0.dist-info/WHEEL
lerobot_surgery-0.1.0.dist-info/entry_points.txt
lerobot_surgery-0.1.0.dist-info/top_level.txt
lerobot_surgery-0.1.0.dist-info/RECORD
