Metadata-Version: 2.4
Name: lerobot-surgery
Version: 0.1.0
Summary: Dataset surgery utils (e.g., merge, episode remove) for LeRobotDataset v3
Author: Giacomo Spigler <http://www.spigler.net/giacomo>
License: MIT
Project-URL: Homepage, https://github.com/spiglerg/lerobot-surgery
Project-URL: Documentation, https://github.com/spiglerg/lerobot-surgery#readme
Project-URL: Repository, https://github.com/spiglerg/lerobot-surgery
Project-URL: Issues, https://github.com/spiglerg/lerobot-surgery/issues
Keywords: robotics,lerobot,dataset
Classifier: Development Status :: 4 - Beta
Classifier: Intended Audience :: Science/Research
Classifier: Intended Audience :: Developers
Classifier: License :: OSI Approved :: MIT License
Classifier: Programming Language :: Python :: 3
Classifier: Topic :: Scientific/Engineering :: Artificial Intelligence
Requires-Python: >=3.8
License-File: LICENSE
Requires-Dist: lerobot>=0.4.0
Requires-Dist: datasets>=2.0.0
Requires-Dist: torch>=1.13.0
Requires-Dist: numpy>=1.21.0
Requires-Dist: click>=8.0.0
Requires-Dist: tqdm>=4.65.0
Provides-Extra: dev
Requires-Dist: pytest>=7.0.0; extra == "dev"
Requires-Dist: pytest-cov>=4.0.0; extra == "dev"
Requires-Dist: black>=23.0.0; extra == "dev"
Requires-Dist: ruff>=0.1.0; extra == "dev"
Dynamic: license-file
